setup.cfg
setup.py
validada/__init__.py
validada/convenience.py
validada/core.py
validada/slicers.py
validada.egg-info/PKG-INFO
validada.egg-info/SOURCES.txt
validada.egg-info/dependency_links.txt
validada.egg-info/requires.txt
validada.egg-info/top_level.txt
validada/decorators/__init__.py
validada/decorators/raising.py
validada/decorators/returning.py
validada/functions/__init__.py
validada/functions/raising.py
validada/functions/returning.py