Metadata-Version: 1.1
Name: validada
Version: 0.0.1
Summary: A python package for defensive data analysis.
Home-page: https://github.com/jnmclarty/validada
Author: Jeffrey McLarty
Author-email: jeffrey.mclarty@gmail.com
License: MIT
Keywords: data analysis,engarde,validata,valid data,validada,asster,asstr
Platform: UNKNOWN
Classifier: Development Status :: 3 - Alpha
Classifier: Intended Audience :: Developers
Classifier: License :: OSI Approved :: MIT License
Classifier: Programming Language :: Python :: 2.7
